LICENSE
MANIFEST.in
README.rst
setup.cfg
setup.py
tentacle/__about__.py
tentacle/__init__.py
tentacle/__main__.py
tentacle/app.py
tentacle/cmds.py
tentacle/tentacle.cfg
tentacle/util.py
tentacle.egg-info/PKG-INFO
tentacle.egg-info/SOURCES.txt
tentacle.egg-info/dependency_links.txt
tentacle.egg-info/entry_points.txt
tentacle.egg-info/not-zip-safe
tentacle.egg-info/requires.txt
tentacle.egg-info/top_level.txt
tentacle/client/__init__.py
tentacle/client/cam.py
tentacle/client/files.py
tentacle/client/model.py
tentacle/client/octo.py
tentacle/scripts/backlight
tentacle/ui/__init__.py
tentacle/ui/cam.py
tentacle/ui/files.py
tentacle/ui/gcode.py
tentacle/ui/job.py
tentacle/ui/move.py
tentacle/ui/serial.py
tentacle/ui/temp.py
tentacle/ui/tool.py