Metadata-Version: 1.2
Name: tentacle
Version: 1.0.0
Summary: An OctoPrint frontend suitable for small displays
Home-page: https://github.com/cnvogelg/tentacle
Author: Christian Vogelgsang
Author-email: chris@vogelgsang.org
License: GPLv3+
Platform: UNKNOWN
Requires-Python: ~=3.4
